vendorless/core/__init__.py
vendorless/core/blueprints/__init__.py
vendorless/core/cli.py
vendorless/core/commands.py
vendorless/core/parameters.py
vendorless/core/service_template.py
vendorless/core/templates/package/cookiecutter.json
vendorless/core/templates/package/{{cookiecutter.name}}/.github/workflows/gh-pages.yaml
vendorless/core/templates/package/{{cookiecutter.name}}/.github/workflows/pypi.yaml
vendorless/core/templates/package/{{cookiecutter.name}}/.github/workflows/pytest.yaml
vendorless/core/templates/package/{{cookiecutter.name}}/README.md
vendorless/core/templates/package/{{cookiecutter.name}}/docs/blueprints.md
vendorless/core/templates/package/{{cookiecutter.name}}/docs/index.md
vendorless/core/templates/package/{{cookiecutter.name}}/docs/service-templates.md
vendorless/core/templates/package/{{cookiecutter.name}}/mkdocs.yml
vendorless/core/templates/package/{{cookiecutter.name}}/pyproject.toml
vendorless/core/templates/package/{{cookiecutter.name}}/src/vendorless/{{cookiecutter.name}}/__init__.py
vendorless/core/templates/package/{{cookiecutter.name}}/src/vendorless/{{cookiecutter.name}}/blueprints/__init__.py
vendorless/core/templates/package/{{cookiecutter.name}}/src/vendorless/{{cookiecutter.name}}/commands.py
vendorless/core/templates/volume/docker-compose.yaml
vendorless/core/templating.py
vendorless/core/volume.py
vendorless_core-0.1.5.dist-info/METADATA
vendorless_core-0.1.5.dist-info/WHEEL
vendorless_core-0.1.5.dist-info/entry_points.txt
vendorless_core-0.1.5.dist-info/RECORD
